fhan/__init__.py
fhan/client/__init__.py
fhan/client/client.py
fhan/client/client_test.py
fhan/client/exceptions.py
fhan/client/issue_types.py
fhan/client/log.py
fhan/client/resource_type.py
fhan/client/search_builder.py
fhan/client/search_bundle.py
fhan/client/utils.py
fhan/client/utils_test.py
fhan/client/generated/search_builder.py
fhan/client/generated/search_builder_mixin.py
fhan/client/generated/search_resource_mixin.py
fhan/client/scripts/__init__.py
fhan/client/scripts/create_from_template.py
fhan/client/scripts/templates/get_resource_mixin.j2
fhan/client/scripts/templates/search_builder.j2
fhan/client/scripts/templates/search_builder_mixin.j2
fhan/client/scripts/templates/search_resource_mixin.j2
fhan-0.1.16.dist-info/METADATA
fhan-0.1.16.dist-info/WHEEL
fhan-0.1.16.dist-info/entry_points.txt
fhan-0.1.16.dist-info/licenses/LICENSE
fhan-0.1.16.dist-info/RECORD
