Metadata-Version: 2.3
Name: fhan
Version: 0.1.16
Summary: Add your description here
Author-email: Till Rostalski <tillrostalski@gmail.com>
License-File: LICENSE
Requires-Python: >=3.10
Requires-Dist: fhirmodels>=0.1.3
Requires-Dist: python-dotenv>=1.0.0
Requires-Dist: requests>=2.31.0
Requires-Dist: structlog>=22.1.0
